orofacIAnalysis/__init__.py
orofacIAnalysis/chew_annotator.py
orofacIAnalysis/cycle.py
orofacIAnalysis/face.py
orofacIAnalysis/landmarks.py
orofacIAnalysis/posture.py
orofacIAnalysis/smoothing.py
orofacIAnalysis/utils.py
orofacIAnalysis/detectors/__init__.py
orofacIAnalysis/detectors/base.py
orofacIAnalysis/detectors/dlib_detector.py
orofacIAnalysis/detectors/mediapipe.py
orofacianalysis-0.1.2.dist-info/licenses/LICENSE
tests/__init__.py
tests/conftest.py
tests/test_orofacIAnalysis.py
tests/test_resources/__init__.py
orofacianalysis-0.1.2.dist-info/METADATA
orofacianalysis-0.1.2.dist-info/WHEEL
orofacianalysis-0.1.2.dist-info/top_level.txt
orofacianalysis-0.1.2.dist-info/RECORD
