Metadata-Version: 2.4
Name: orofacIAnalysis
Version: 0.1.2
Summary: A library for analyzing chewing patterns using computer vision
Home-page: https://github.com/yourusername/orofacIAnalysis
Author: Cameron Maloney
Author-email: cameron.maloney@warriorlife.net
Classifier: Programming Language :: Python :: 3
Classifier: License :: OSI Approved :: MIT License
Classifier: Operating System :: OS Independent
Requires-Python: >=3.7
License-File: LICENSE
Requires-Dist: numpy>=1.20.0
Requires-Dist: opencv-python>=4.5.0
Requires-Dist: mediapipe>=0.8.10
Requires-Dist: scipy>=1.7.0
Requires-Dist: pandas>=1.3.0
Requires-Dist: matplotlib>=3.4.0
Requires-Dist: PyEMD>=0.2.0
Requires-Dist: statsmodels>=0.13.0
Dynamic: author
Dynamic: author-email
Dynamic: classifier
Dynamic: description
Dynamic: description-content-type
Dynamic: home-page
Dynamic: license-file
Dynamic: requires-dist
Dynamic: requires-python
Dynamic: summary
